django_js_choices/__init__.py
django_js_choices/core.py
django_js_choices/js_choices_settings.py
django_js_choices/management/__init__.py
django_js_choices/management/commands/__init__.py
django_js_choices/management/commands/collectstatic_js_choices.py
django_js_choices/models.py
django_js_choices/templates/django_js_choices/choices_js.tpl
django_js_choices/templatetags/__init__.py
django_js_choices/templatetags/js_choices.py
django_js_choices/views.py
django_js_choices-0.6.0.dist-info/LICENSE
django_js_choices-0.6.0.dist-info/METADATA
django_js_choices-0.6.0.dist-info/WHEEL
django_js_choices-0.6.0.dist-info/RECORD
