Metadata-Version: 2.1
Name: django-js-choices
Version: 0.6.0
Summary: Javascript model field choices handling for Django.
Home-page: https://github.com/lorinkoz/django-js-choices
License: MIT
Keywords: django,choices,javascript
Author: Lorenzo Peña
Author-email: lorinkoz@gmail.com
Requires-Python: >=3.10,<4.0
Classifier: Development Status :: 4 - Beta
Classifier: Framework :: Django
Classifier: Framework :: Django :: 5.0
Classifier: Framework :: Django :: 5.1
Classifier: License :: OSI Approved :: MIT License
Classifier: Programming Language :: Python :: 3
Classifier: Programming Language :: Python :: 3.10
Classifier: Programming Language :: Python :: 3.11
Classifier: Programming Language :: Python :: 3.12
Classifier: Programming Language :: Python :: 3.13
Requires-Dist: django (>=5.0,<6.0)
Requires-Dist: rjsmin (>=1.1.0,<2.0.0)
Project-URL: Repository, https://github.com/lorinkoz/django-js-choices
